musical_scales/__init__.py
musical_scales-2.0.0.dist-info/METADATA
musical_scales-2.0.0.dist-info/WHEEL
musical_scales-2.0.0.dist-info/top_level.txt
musical_scales-2.0.0.dist-info/RECORD
