Metadata-Version: 2.4
Name: musical-scales
Version: 2.0.0
Summary: Retrieve a scale based on a given mode and starting note.
Home-page: https://github.com/hmillerbakewell/musical-scales
Author: Hector Miller-Bakewell
Author-email: hmillerbakewell@gmail.com
License: MIT
Project-URL: Bug Tracker, https://github.com/hmillerbakewell/musical-scales
Classifier: Programming Language :: Python :: 3
Classifier: Programming Language :: Python :: 3.10
Classifier: License :: OSI Approved :: MIT License
Classifier: Operating System :: OS Independent
Requires-Python: >=3.10
